deaplog/__init__.py
deaplog/deaplog.py
deaplog-1.1.0.dist-info/METADATA
deaplog-1.1.0.dist-info/WHEEL
deaplog-1.1.0.dist-info/licenses/LICENSE.txt
deaplog-1.1.0.dist-info/RECORD
