Metadata-Version: 2.1
Name: deaplog
Version: 1.1.0
Summary: A tool to perform differentially expression analysis and calculate the pseudotime and coodinates of genes by using single cell RNA-seq data
Project-URL: Homepage, https://github.com/ZhangHongbo-Lab/DEAPLOG
Project-URL: Bug Tracker, https://github.com/ZhangHongbo-Lab/DEAPLOG/issues
Author-email: BaoZhang <zhangbao5@mail.sysu.edu.cn>
License-File: LICENSE.txt
Classifier: License :: OSI Approved :: MIT License
Classifier: Operating System :: OS Independent
Classifier: Programming Language :: Python :: 3
Requires-Python: >=3.9
Requires-Dist: anndata
Requires-Dist: cython
Requires-Dist: datetime
Requires-Dist: fisher
Requires-Dist: matplotlib
Requires-Dist: networkx
Requires-Dist: numpy
Requires-Dist: pandas
Requires-Dist: scanpy
Requires-Dist: scikit-learn
Requires-Dist: scipy
Requires-Dist: sympy
